lib_h/__init__.py
lib_h/rectangle.py
lib_h-0.1.0.dist-info/METADATA
lib_h-0.1.0.dist-info/WHEEL
lib_h-0.1.0.dist-info/RECORD
